openml_speed_dating_pipeline_steps/__init__.py
openml_speed_dating_pipeline_steps/openml_speed_dating_pipeline_steps.py
openml_speed_dating_pipeline_steps-0.5.6.dist-info/LICENSE
openml_speed_dating_pipeline_steps-0.5.6.dist-info/METADATA
openml_speed_dating_pipeline_steps-0.5.6.dist-info/WHEEL
openml_speed_dating_pipeline_steps-0.5.6.dist-info/top_level.txt
openml_speed_dating_pipeline_steps-0.5.6.dist-info/RECORD
