Metadata-Version: 2.1
Name: openml-speed-dating-pipeline-steps
Version: 0.5.6
Summary: This contains all the steps needed to
Home-page: https://github.com/benman1/openml_speed_dating_pipeline_steps
Author: Ben Auffarth
Author-email: auffarth@gmail.com
License: MIT license
Keywords: openml_speed_dating_pipeline_steps
Platform: UNKNOWN
Classifier: Development Status :: 2 - Pre-Alpha
Classifier: Intended Audience :: Developers
Classifier: License :: OSI Approved :: MIT License
Classifier: Natural Language :: English
Classifier: Programming Language :: Python :: 3
Classifier: Programming Language :: Python :: 3.5
Classifier: Programming Language :: Python :: 3.6
Classifier: Programming Language :: Python :: 3.7
Classifier: Programming Language :: Python :: 3.8
Requires-Python: >=3.5
Requires-Dist: numpy
Requires-Dist: pandas
Requires-Dist: scikit-learn
Requires-Dist: category-encoders (>=2.0.0)
Requires-Dist: numba
